ni/measurementlink/sessionmanagement/v1/client/__init__.py
ni/measurementlink/sessionmanagement/v1/client/_annotations.py
ni/measurementlink/sessionmanagement/v1/client/_client.py
ni/measurementlink/sessionmanagement/v1/client/_client_base.py
ni/measurementlink/sessionmanagement/v1/client/_constants.py
ni/measurementlink/sessionmanagement/v1/client/_drivers/__init__.py
ni/measurementlink/sessionmanagement/v1/client/_drivers/_configuration.py
ni/measurementlink/sessionmanagement/v1/client/_drivers/_dotenvpath.py
ni/measurementlink/sessionmanagement/v1/client/_drivers/_grpcdevice.py
ni/measurementlink/sessionmanagement/v1/client/_drivers/_nidaqmx.py
ni/measurementlink/sessionmanagement/v1/client/_drivers/_nidcpower.py
ni/measurementlink/sessionmanagement/v1/client/_drivers/_nidigital.py
ni/measurementlink/sessionmanagement/v1/client/_drivers/_nidmm.py
ni/measurementlink/sessionmanagement/v1/client/_drivers/_nifgen.py
ni/measurementlink/sessionmanagement/v1/client/_drivers/_niscope.py
ni/measurementlink/sessionmanagement/v1/client/_drivers/_niswitch.py
ni/measurementlink/sessionmanagement/v1/client/_reservation.py
ni/measurementlink/sessionmanagement/v1/client/_types.py
ni/measurementlink/sessionmanagement/v1/client/py.typed
ni_measurementlink_sessionmanagement_v1_client-1.1.0.dist-info/METADATA
ni_measurementlink_sessionmanagement_v1_client-1.1.0.dist-info/WHEEL
ni_measurementlink_sessionmanagement_v1_client-1.1.0.dist-info/RECORD
