Metadata-Version: 2.3
Name: ni.measurementlink.sessionmanagement.v1.client
Version: 1.1.0
Summary: Client gRPC APIs for the session management service
License: MIT
Keywords: ni-apis,sessionmanagement
Author: NI
Author-email: opensource@ni.com
Maintainer: Joe Friedrichsen
Maintainer-email: joe.friedrichsen@emerson.com
Requires-Python: >=3.10,<4.0
Classifier: Development Status :: 5 - Production/Stable
Classifier: Intended Audience :: Developers
Classifier: Intended Audience :: Manufacturing
Classifier: Intended Audience :: Science/Research
Classifier: License :: OSI Approved :: MIT License
Classifier: Operating System :: Microsoft :: Windows
Classifier: Operating System :: POSIX
Classifier: Programming Language :: Python :: 3
Classifier: Programming Language :: Python :: 3.10
Classifier: Programming Language :: Python :: 3.11
Classifier: Programming Language :: Python :: 3.12
Classifier: Programming Language :: Python :: 3.13
Classifier: Programming Language :: Python :: 3.14
Classifier: Programming Language :: Python :: Implementation :: CPython
Provides-Extra: drivers
Provides-Extra: nidaqmx
Provides-Extra: nidcpower
Provides-Extra: nidigital
Provides-Extra: nidmm
Provides-Extra: nifgen
Provides-Extra: niscope
Provides-Extra: niswitch
Requires-Dist: deprecation (>=2.1)
Requires-Dist: ni-grpc-extensions (>=1.1.0)
Requires-Dist: ni-grpcdevice-v1-proto (>=1.1.0)
Requires-Dist: ni-measurementlink-discovery-v1-client (>=1.1.0)
Requires-Dist: ni-measurementlink-pinmap-v1-proto (>=1.1.0)
Requires-Dist: ni-measurementlink-proto (>=1.1.0)
Requires-Dist: ni-measurementlink-sessionmanagement-v1-proto (>=1.1.0)
Requires-Dist: nidaqmx[grpc] (>=0.8.0) ; extra == "drivers" or extra == "nidaqmx"
Requires-Dist: nidcpower[grpc] (>=1.4.4) ; extra == "drivers" or extra == "nidcpower"
Requires-Dist: nidigital[grpc] (>=1.4.4) ; extra == "drivers" or extra == "nidigital"
Requires-Dist: nidmm[grpc] (>=1.4.4) ; extra == "drivers" or extra == "nidmm"
Requires-Dist: nifgen[grpc] (>=1.4.4) ; extra == "drivers" or extra == "nifgen"
Requires-Dist: niscope[grpc] (>=1.4.4) ; extra == "drivers" or extra == "niscope"
Requires-Dist: niswitch[grpc] (>=1.4.4) ; extra == "drivers" or extra == "niswitch"
Requires-Dist: protobuf (>=4.21)
Requires-Dist: python-decouple (>=3.8)
Requires-Dist: pywin32 (>=303) ; sys_platform == "win32"
Requires-Dist: traceloggingdynamic (>=1.0) ; sys_platform == "win32"
Project-URL: Documentation, https://nimeasurementlinksessionmanagementclient.readthedocs.io/en/latest/
Project-URL: Repository, https://github.com/ni/ni-apis-python
